fnexchange/__init__.py
fnexchange/cli.py
fnexchange/core/__init__.py
fnexchange/core/config.py
fnexchange/core/exceptions.py
fnexchange/core/plugins.py
fnexchange/server/__init__.py
fnexchange/server/app.py
fnexchange/server/exceptions.py
fnexchange/server/handlers.py
fnexchange-0.2.1.dist-info/DESCRIPTION.rst
fnexchange-0.2.1.dist-info/METADATA
fnexchange-0.2.1.dist-info/RECORD
fnexchange-0.2.1.dist-info/WHEEL
fnexchange-0.2.1.dist-info/entry_points.txt
fnexchange-0.2.1.dist-info/metadata.json
fnexchange-0.2.1.dist-info/top_level.txt
