Metadata-Version: 2.0
Name: fnexchange
Version: 0.2.1
Summary: fnExchange API router and management CLI
Home-page: https://github.com/dnif/fnExchange
Author: Bhumil Haria
Author-email: bhumilharia@gmail.com
License: Apache
Keywords: fnexchange api router orchestration
Platform: any
Classifier: Development Status :: 4 - Beta
Classifier: Intended Audience :: Developers
Classifier: License :: OSI Approved :: Apache Software License
Classifier: Operating System :: POSIX
Classifier: Operating System :: MacOS
Classifier: Operating System :: Unix
Classifier: Operating System :: Microsoft :: Windows
Classifier: Programming Language :: Python
Classifier: Programming Language :: Python :: 2
Classifier: Programming Language :: Python :: 3
Requires-Dist: PyYAML (==3.12)
Requires-Dist: click (==6.7)
Requires-Dist: requests (>=2.4.2)
Requires-Dist: six (==1.10.0)
Requires-Dist: tornado (==4.4.2)
